helasentilex/__init__.py
helasentilex/lexicon.csv
helasentilex-0.1.1.dist-info/LICENSE
helasentilex-0.1.1.dist-info/METADATA
helasentilex-0.1.1.dist-info/WHEEL
helasentilex-0.1.1.dist-info/top_level.txt
helasentilex-0.1.1.dist-info/RECORD
