Metadata-Version: 2.1
Name: helasentilex
Version: 0.1.1
Summary: Python API for Sinhala Sentiment Lexicon
Home-page: https://github.com/binodmx/helasentilex
Author: Binod Karunanayake
Author-email: binod.16@cse.mrt.ac.lk
License: UNKNOWN
Platform: UNKNOWN
Classifier: Programming Language :: Python :: 3
Classifier: License :: OSI Approved :: MIT License
Classifier: Operating System :: OS Independent
Requires-Python: >=3.6
